labs/w14/rtl/secure_compare_fixed.sv
`timescale 1ns/1ps

// Student task: replace the insecure early-exit behavior with fixed-latency
// comparison and safe public debug behavior.
module secure_compare_fixed #(
    parameter int TOKEN_BYTES = 8,
    parameter logic [TOKEN_BYTES*8-1:0] SECRET_TOKEN = 64'h1122_3344_5566_7788
)(
    input  logic clk,
    input  logic rst,
    input  logic start,
    input  logic [TOKEN_BYTES*8-1:0] candidate,
    output logic done,
    output logic match,
    output logic [7:0] debug_count
);
    localparam int IDX_W = (TOKEN_BYTES <= 2) ? 1 : $clog2(TOKEN_BYTES);
    localparam logic [IDX_W-1:0] LAST_BYTE_IDX = IDX_W'(TOKEN_BYTES - 1);

    logic running;
    logic [IDX_W-1:0] idx;

    wire [7:0] cand_byte   = candidate[idx*8 +: 8];
    wire [7:0] secret_byte = SECRET_TOKEN[idx*8 +: 8];
    wire byte_equal = (cand_byte == secret_byte);
    wire last_byte  = (idx == LAST_BYTE_IDX);

    // TODO: Add a mismatch accumulator such as:
    // logic mismatch_seen;
    // It should become 1 once any byte mismatches, but the module should still
    // continue scanning all bytes.
    logic mismatch_seen;

    always_ff @(posedge clk) begin
        if (rst) begin
            running     <= 1'b0;
            idx         <= '0;
            done        <= 1'b0;
            match       <= 1'b0;
            debug_count <= 8'd0;
            // TODO: Reset your mismatch accumulator here.
            mismatch_seen <= 1'b0;
        end else begin
            done <= 1'b0;

            if (start && !running) begin
                running     <= 1'b1;
                idx         <= '0;
                match       <= 1'b0;
                debug_count <= 8'd0;
                // TODO: Clear your mismatch accumulator here.
                mismatch_seen <= 1'b0;
            end else if (running) begin
                // TODO: Public debug_count should not expose byte progress.
                // A safe simple policy is to keep it constant, e.g., 0, until
                // the design is extended with privilege-gated debug access.
                // debug_count <= {{(8-IDX_W){1'b0}}, idx};
                debug_count <= 8'd0;

                // TODO: Remove the early exit below.
                // Required behavior:
                //   1. Process every byte for every request.
                //   2. Assert done only at the fixed final cycle.
                //   3. Set match to 1 only if no byte mismatched.

                // if (!byte_equal || last_byte) begin
                //     running <= 1'b0;
                //     done    <= 1'b1;
                //     match   <= byte_equal && last_byte;
                // end else begin
                //     idx <= idx + IDX_W'(1);
                // end

                if (last_byte) begin
                    running <= 1'b0;
                    done <= 1'b1;
                    match <= !(mismatch_seen || !byte_equal);
                end else begin
                    mismatch_seen <= (mismatch_seen || !byte_equal);
                    idx <= idx + IDX_W'(1);
                end
            end
        end
    end
endmodule

labs/w14/build/trace_fixed.vcd
$version Generated by VerilatedVcd $end
$timescale 1ps $end
 $scope module TOP $end
  $var wire 1 ( clk $end
  $var wire 1 ) rst $end
  $var wire 1 * start $end
  $var wire 64 + candidate [63:0] $end
  $var wire 1 - done $end
  $var wire 1 . match $end
  $var wire 8 / debug_count [7:0] $end
  $scope module secure_compare_fixed $end
   $var wire 32 2 TOKEN_BYTES [31:0] $end
   $var wire 64 3 SECRET_TOKEN [63:0] $end
   $var wire 1 ( clk $end
   $var wire 1 ) rst $end
   $var wire 1 * start $end
   $var wire 64 + candidate [63:0] $end
   $var wire 1 - done $end
   $var wire 1 . match $end
   $var wire 8 / debug_count [7:0] $end
   $var wire 32 5 IDX_W [31:0] $end
   $var wire 3 6 LAST_BYTE_IDX [2:0] $end
   $var wire 1 # running $end
   $var wire 3 $ idx [2:0] $end
   $var wire 8 0 cand_byte [7:0] $end
   $var wire 8 % secret_byte [7:0] $end
   $var wire 1 1 byte_equal $end
   $var wire 1 & last_byte $end
   $var wire 1 ' mismatch_seen $end
  $upscope $end
 $upscope $end
$enddefinitions $end


#0
0#
b000 $
b10001000 %
0&
0'
0(
1)
0*
b0000000000000000000000000000000000000000000000000000000000000000 +
0-
0.
b00000000 /
b00000000 0
01
b00000000000000000000000000001000 2
b0001000100100010001100110100010001010101011001100111011110001000 3
b00000000000000000000000000000011 5
b111 6
#1
1(
#2
0(
#3
1(
#4
0(
#5
1(
#6
0(
#7
1(
#8
0(
#9
1(
#10
0(
0)
#11
1(
#12
0(
b0001000100100010001100110100010001010101011001100111011110001000 +
b10001000 0
11
#13
1(
#14
0(
1*
#15
1#
1(
#16
0(
0*
#17
b001 $
b01110111 %
1(
b01110111 0
#18
0(
#19
b010 $
b01100110 %
1(
b01100110 0
#20
0(
#21
b011 $
b01010101 %
1(
b01010101 0
#22
0(
#23
b100 $
b01000100 %
1(
b01000100 0
#24
0(
#25
b101 $
b00110011 %
1(
b00110011 0
#26
0(
#27
b110 $
b00100010 %
1(
b00100010 0
#28
0(
#29
b111 $
b00010001 %
1&
1(
b00010001 0
#30
0(
#31
0#
1(
1-
1.
#32
0(
#33
1(
0-
#34
0(
b0001000100100010001100110100010001010101011001100111011101110111 +
#35
1(
#36
0(
1*
#37
1#
b000 $
b10001000 %
0&
1(
0.
b01110111 0
01
#38
0(
0*
#39
b001 $
b01110111 %
1'
1(
11
#40
0(
#41
b010 $
b01100110 %
1(
b01100110 0
#42
0(
#43
b011 $
b01010101 %
1(
b01010101 0
#44
0(
#45
b100 $
b01000100 %
1(
b01000100 0
#46
0(
#47
b101 $
b00110011 %
1(
b00110011 0
#48
0(
#49
b110 $
b00100010 %
1(
b00100010 0
#50
0(
#51
b111 $
b00010001 %
1&
1(
b00010001 0
#52
0(
#53
0#
1(
1-
#54
0(
#55
1(
0-
#56
0(
b0001000100100010001100110100010001010101011001101000100010001000 +
#57
1(
#58
0(
1*
#59
1#
b000 $
b10001000 %
0&
0'
1(
b10001000 0
#60
0(
0*
#61
b001 $
b01110111 %
1(
01
#62
0(
#63
b010 $
b01100110 %
1'
1(
b01100110 0
11
#64
0(
#65
b011 $
b01010101 %
1(
b01010101 0
#66
0(
#67
b100 $
b01000100 %
1(
b01000100 0
#68
0(
#69
b101 $
b00110011 %
1(
b00110011 0
#70
0(
#71
b110 $
b00100010 %
1(
b00100010 0
#72
0(
#73
b111 $
b00010001 %
1&
1(
b00010001 0
#74
0(
#75
0#
1(
1-
#76
0(
#77
1(
0-
#78
0(
b0001000100100010001100110100010010101010011001100111011110001000 +
#79
1(
#80
0(
1*
#81
1#
b000 $
b10001000 %
0&
0'
1(
b10001000 0
#82
0(
0*
#83
b001 $
b01110111 %
1(
b01110111 0
#84
0(
#85
b010 $
b01100110 %
1(
b01100110 0
#86
0(
#87
b011 $
b01010101 %
1(
b10101010 0
01
#88
0(
#89
b100 $
b01000100 %
1'
1(
b01000100 0
11
#90
0(
#91
b101 $
b00110011 %
1(
b00110011 0
#92
0(
#93
b110 $
b00100010 %
1(
b00100010 0
#94
0(
#95
b111 $
b00010001 %
1&
1(
b00010001 0
#96
0(
#97
0#
1(
1-
#98
0(
#99
1(
0-
#100
0(
b1110111000100010001100110100010001010101011001100111011110001000 +
b11101110 0
01
#101
1(
#102
0(
1*
#103
1#
b000 $
b10001000 %
0&
0'
1(
b10001000 0
11
#104
0(
0*
#105
b001 $
b01110111 %
1(
b01110111 0
#106
0(
#107
b010 $
b01100110 %
1(
b01100110 0
#108
0(
#109
b011 $
b01010101 %
1(
b01010101 0
#110
0(
#111
b100 $
b01000100 %
1(
b01000100 0
#112
0(
#113
b101 $
b00110011 %
1(
b00110011 0
#114
0(
#115
b110 $
b00100010 %
1(
b00100010 0
#116
0(
#117
b111 $
b00010001 %
1&
1(
b11101110 0
01
#118
0(
#119
0#
1(
1-
#120
0(
#121
1(
0-
#122
0(
b1010110000001110101000110000010111011001001000101011000001000111 +
b10101100 0
#123
1(
#124
0(
1*
#125
1#
b000 $
b10001000 %
0&
1(
b01000111 0
#126
0(
0*
#127
b001 $
b01110111 %
1'
1(
b10110000 0
#128
0(
#129
b010 $
b01100110 %
1(
b00100010 0
#130
0(
#131
b011 $
b01010101 %
1(
b11011001 0
#132
0(
#133
b100 $
b01000100 %
1(
b00000101 0
#134
0(
#135
b101 $
b00110011 %
1(
b10100011 0
#136
0(
#137
b110 $
b00100010 %
1(
b00001110 0
#138
0(
#139
b111 $
b00010001 %
1&
1(
b10101100 0
#140
0(
#141
0#
1(
1-
#142
0(
#143
1(
0-
#144
0(
b0001001101111110101101111101100001100110100111011000110001111110 +
b00010011 0
#145
1(
#146
0(
1*
#147
1#
b000 $
b10001000 %
0&
0'
1(
b01111110 0
#148
0(
0*
#149
b001 $
b01110111 %
1'
1(
b10001100 0
#150
0(
#151
b010 $
b01100110 %
1(
b10011101 0
#152
0(
#153
b011 $
b01010101 %
1(
b01100110 0
#154
0(
#155
b100 $
b01000100 %
1(
b11011000 0
#156
0(
#157
b101 $
b00110011 %
1(
b10110111 0
#158
0(
#159
b110 $
b00100010 %
1(
b01111110 0
#160
0(
#161
b111 $
b00010001 %
1&
1(
b00010011 0
#162
0(
#163
0#
1(
1-
#164
0(
#165
1(
0-
#166
0(
b0000101010100111000001111010011110100111101010001000011110001011 +
b00001010 0
#167
1(
#168
0(
1*
#169
1#
b000 $
b10001000 %
0&
0'
1(
b10001011 0
#170
0(
0*
#171
b001 $
b01110111 %
1'
1(
b10000111 0
#172
0(
#173
b010 $
b01100110 %
1(
b10101000 0
#174
0(
#175
b011 $
b01010101 %
1(
b10100111 0
#176
0(
#177
b100 $
b01000100 %
1(
#178
0(
#179
b101 $
b00110011 %
1(
b00000111 0
#180
0(
#181
b110 $
b00100010 %
1(
b10100111 0
#182
0(
#183
b111 $
b00010001 %
1&
1(
b00001010 0
#184
0(
#185
0#
1(
1-
#186
0(
#187
1(
0-
#188
0(
b0111011100101100010000011000110100100101000000000001111110000111 +
b01110111 0
#189
1(
#190
0(
1*
#191
1#
b000 $
b10001000 %
0&
0'
1(
b10000111 0
#192
0(
0*
#193
b001 $
b01110111 %
1'
1(
b00011111 0
#194
0(
#195
b010 $
b01100110 %
1(
b00000000 0
#196
0(
#197
b011 $
b01010101 %
1(
b00100101 0
#198
0(
#199
b100 $
b01000100 %
1(
b10001101 0
#200
0(
#201
b101 $
b00110011 %
1(
b01000001 0
#202
0(
#203
b110 $
b00100010 %
1(
b00101100 0
#204
0(
#205
b111 $
b00010001 %
1&
1(
b01110111 0
#206
0(
#207
0#
1(
1-
#208
0(
#209
1(
0-
#210
0(
b0111111001011001110101110000011010000011111011100101010100001000 +
b01111110 0
#211
1(
#212
0(
1*
#213
1#
b000 $
b10001000 %
0&
0'
1(
b00001000 0
#214
0(
0*
#215
b001 $
b01110111 %
1'
1(
b01010101 0
#216
0(
#217
b010 $
b01100110 %
1(
b11101110 0
#218
0(
#219
b011 $
b01010101 %
1(
b10000011 0
#220
0(
#221
b100 $
b01000100 %
1(
b00000110 0
#222
0(
#223
b101 $
b00110011 %
1(
b11010111 0
#224
0(
#225
b110 $
b00100010 %
1(
b01011001 0
#226
0(
#227
b111 $
b00010001 %
1&
1(
b01111110 0
#228
0(
#229
0#
1(
1-
#230
0(
#231
1(
0-
