labs/w14/rtl/secure_compare_buggy.sv
`timescale 1ns/1ps

// Deliberately insecure design for Week 14 exercise.
// It exits as soon as a mismatching byte is found, so completion latency leaks
// the first mismatching byte position.
module secure_compare_buggy #(
    parameter int TOKEN_BYTES = 8,
    parameter logic [TOKEN_BYTES*8-1:0] SECRET_TOKEN = 64'h1122_3344_5566_7788
)(
    input  logic clk,
    input  logic rst,
    input  logic start,
    input  logic [TOKEN_BYTES*8-1:0] candidate,
    output logic done,
    output logic match,
    output logic [7:0] debug_count
);
    localparam int IDX_W = (TOKEN_BYTES <= 2) ? 1 : $clog2(TOKEN_BYTES);
    localparam logic [IDX_W-1:0] LAST_BYTE_IDX = IDX_W'(TOKEN_BYTES - 1);

    logic running;
    logic [IDX_W-1:0] idx;

    wire [7:0] cand_byte   = candidate[idx*8 +: 8];
    wire [7:0] secret_byte = SECRET_TOKEN[idx*8 +: 8];
    wire byte_equal = (cand_byte == secret_byte);
    wire last_byte  = (idx == LAST_BYTE_IDX);

    always_ff @(posedge clk) begin
        if (rst) begin
            running     <= 1'b0;
            idx         <= '0;
            done        <= 1'b0;
            match       <= 1'b0;
            debug_count <= 8'd0;
        end else begin
            done <= 1'b0;

            if (start && !running) begin
                running     <= 1'b1;
                idx         <= '0;
                match       <= 1'b0;
                debug_count <= 8'd0;
            end else if (running) begin
                // BUG 1: Public debug_count reveals the current byte index.
                debug_count <= {{(8-IDX_W){1'b0}}, idx};

                // BUG 2: Early exit leaks mismatch position through done timing.
                if (!byte_equal || last_byte) begin
                    running <= 1'b0;
                    done    <= 1'b1;
                    match   <= byte_equal && last_byte;
                end else begin
                    idx <= idx + 1'b1;
                end
            end
        end
    end
endmodule

labs/w14/build/trace_buggy.vcd
$version Generated by VerilatedVcd $end
$timescale 1ps $end
 $scope module TOP $end
  $var wire 1 ' clk $end
  $var wire 1 ( rst $end
  $var wire 1 ) start $end
  $var wire 64 * candidate [63:0] $end
  $var wire 1 , done $end
  $var wire 1 - match $end
  $var wire 8 . debug_count [7:0] $end
  $scope module secure_compare_buggy $end
   $var wire 32 1 TOKEN_BYTES [31:0] $end
   $var wire 64 2 SECRET_TOKEN [63:0] $end
   $var wire 1 ' clk $end
   $var wire 1 ( rst $end
   $var wire 1 ) start $end
   $var wire 64 * candidate [63:0] $end
   $var wire 1 , done $end
   $var wire 1 - match $end
   $var wire 8 . debug_count [7:0] $end
   $var wire 32 4 IDX_W [31:0] $end
   $var wire 3 5 LAST_BYTE_IDX [2:0] $end
   $var wire 1 # running $end
   $var wire 3 $ idx [2:0] $end
   $var wire 8 / cand_byte [7:0] $end
   $var wire 8 % secret_byte [7:0] $end
   $var wire 1 0 byte_equal $end
   $var wire 1 & last_byte $end
  $upscope $end
 $upscope $end
$enddefinitions $end


#0
0#
b000 $
b10001000 %
0&
0'
1(
0)
b0000000000000000000000000000000000000000000000000000000000000000 *
0,
0-
b00000000 .
b00000000 /
00
b00000000000000000000000000001000 1
b0001000100100010001100110100010001010101011001100111011110001000 2
b00000000000000000000000000000011 4
b111 5
#1
1'
#2
0'
#3
1'
#4
0'
#5
1'
#6
0'
#7
1'
#8
0'
#9
1'
#10
0'
0(
#11
1'
#12
0'
b0001000100100010001100110100010001010101011001100111011110001000 *
b10001000 /
10
#13
1'
#14
0'
1)
#15
1#
1'
#16
0'
0)
#17
b001 $
b01110111 %
1'
b01110111 /
#18
0'
#19
b010 $
b01100110 %
1'
b00000001 .
b01100110 /
#20
0'
#21
b011 $
b01010101 %
1'
b00000010 .
b01010101 /
#22
0'
#23
b100 $
b01000100 %
1'
b00000011 .
b01000100 /
#24
0'
#25
b101 $
b00110011 %
1'
b00000100 .
b00110011 /
#26
0'
#27
b110 $
b00100010 %
1'
b00000101 .
b00100010 /
#28
0'
#29
b111 $
b00010001 %
1&
1'
b00000110 .
b00010001 /
#30
0'
#31
0#
1'
1,
1-
b00000111 .
#32
0'
#33
1'
0,
#34
0'
b0001000100100010001100110100010001010101011001100111011101110111 *
#35
1'
#36
0'
1)
#37
1#
b000 $
b10001000 %
0&
1'
0-
b00000000 .
b01110111 /
00
#38
0'
0)
#39
0#
1'
1,
#40
0'
#41
1'
0,
#42
0'
b0001000100100010001100110100010001010101011001101000100010001000 *
b10001000 /
10
#43
1'
#44
0'
1)
#45
1#
1'
#46
0'
0)
#47
b001 $
b01110111 %
1'
00
#48
0'
#49
0#
1'
1,
b00000001 .
#50
0'
#51
1'
0,
#52
0'
b0001000100100010001100110100010010101010011001100111011110001000 *
b01110111 /
10
#53
1'
#54
0'
1)
#55
1#
b000 $
b10001000 %
1'
b00000000 .
b10001000 /
#56
0'
0)
#57
b001 $
b01110111 %
1'
b01110111 /
#58
0'
#59
b010 $
b01100110 %
1'
b00000001 .
b01100110 /
#60
0'
#61
b011 $
b01010101 %
1'
b00000010 .
b10101010 /
00
#62
0'
#63
0#
1'
1,
b00000011 .
#64
0'
#65
1'
0,
#66
0'
b1110111000100010001100110100010001010101011001100111011110001000 *
b01010101 /
10
#67
1'
#68
0'
1)
#69
1#
b000 $
b10001000 %
1'
b00000000 .
b10001000 /
#70
0'
0)
#71
b001 $
b01110111 %
1'
b01110111 /
#72
0'
#73
b010 $
b01100110 %
1'
b00000001 .
b01100110 /
#74
0'
#75
b011 $
b01010101 %
1'
b00000010 .
b01010101 /
#76
0'
#77
b100 $
b01000100 %
1'
b00000011 .
b01000100 /
#78
0'
#79
b101 $
b00110011 %
1'
b00000100 .
b00110011 /
#80
0'
#81
b110 $
b00100010 %
1'
b00000101 .
b00100010 /
#82
0'
#83
b111 $
b00010001 %
1&
1'
b00000110 .
b11101110 /
00
#84
0'
#85
0#
1'
1,
b00000111 .
#86
0'
#87
1'
0,
#88
0'
b1010110000001110101000110000010111011001001000101011000001000111 *
b10101100 /
#89
1'
#90
0'
1)
#91
1#
b000 $
b10001000 %
0&
1'
b00000000 .
b01000111 /
#92
0'
0)
#93
0#
1'
1,
#94
0'
#95
1'
0,
#96
0'
b0001001101111110101101111101100001100110100111011000110001111110 *
b01111110 /
#97
1'
#98
0'
1)
#99
1#
1'
#100
0'
0)
#101
0#
1'
1,
#102
0'
#103
1'
0,
#104
0'
b0000101010100111000001111010011110100111101010001000011110001011 *
b10001011 /
#105
1'
#106
0'
1)
#107
1#
1'
#108
0'
0)
#109
0#
1'
1,
#110
0'
#111
1'
0,
#112
0'
b0111011100101100010000011000110100100101000000000001111110000111 *
b10000111 /
#113
1'
#114
0'
1)
#115
1#
1'
#116
0'
0)
#117
0#
1'
1,
#118
0'
#119
1'
0,
#120
0'
b0111111001011001110101110000011010000011111011100101010100001000 *
b00001000 /
#121
1'
#122
0'
1)
#123
1#
1'
#124
0'
0)
#125
0#
1'
1,
#126
0'
#127
1'
0,
